{
  "ui.dep_graph.analytics_empty": "No data to analyze. Build the plugin index first.",
  "ui.dep_graph.and_n_more": "...and {n} more",
  "ui.dep_graph.back": "Back",
  "ui.dep_graph.confirm_build_index_body": "No plugin index data. You must run \"Plugin Index\" first to scan DAW projects for plugin references. Build the index now?",
  "ui.dep_graph.empty_all_referenced": "All installed plugins are referenced in scanned projects.",
  "ui.dep_graph.empty_no_plugins_in_project": "No plugins found in this project",
  "ui.dep_graph.empty_no_projects": "No projects indexed",
  "ui.dep_graph.empty_no_refs": "No plugin references found",
  "ui.dep_graph.extreme_plugin_one": "{n} plugin",
  "ui.dep_graph.extreme_plugin_other": "{n} plugins",
  "ui.dep_graph.insight_avg_plugins": "Avg plugins per project",
  "ui.dep_graph.insight_orphaned_installed": "Unused installed plugins",
  "ui.dep_graph.insight_single_use": "Single-use plugins",
  "ui.dep_graph.insight_widely_used": "Used in >50% of projects",
  "ui.dep_graph.most_complex": "Most complex:",
  "ui.dep_graph.most_minimal": "Most minimal:",
  "ui.dep_graph.project_header_plugins_one": "{n} plugin",
  "ui.dep_graph.project_header_plugins_other": "{n} plugins",
  "ui.dep_graph.references_pct": "{count} references ({pct}%)",
  "ui.dep_graph.search_placeholder": "Search plugins and projects...",
  "ui.dep_graph.search_title": "Filter dependency graph results",
  "ui.dep_graph.section_format_breakdown": "Plugin Format Breakdown",
  "ui.dep_graph.section_goto_plugins": "Your Go-To Plugins (>50% of projects)",
  "ui.dep_graph.section_key_insights": "Key Insights",
  "ui.dep_graph.section_project_extremes": "Project Extremes",
  "ui.dep_graph.section_single_use": "Single-Use Plugins (only 1 project)",
  "ui.dep_graph.section_top_manufacturers": "Top Manufacturers",
  "ui.dep_graph.stat_orphaned": "Orphaned Plugins",
  "ui.dep_graph.stat_projects_indexed": "Projects Indexed",
  "ui.dep_graph.stat_total_refs": "Total References",
  "ui.dep_graph.stat_unique_plugins": "Unique Plugins",
  "ui.dep_graph.tab_analytics": "Analytics",
  "ui.dep_graph.tab_by_project": "By Project",
  "ui.dep_graph.tab_most_used": "Most Used",
  "ui.dep_graph.tab_orphaned": "Orphaned ({n})",
  "ui.dep_graph.title": "Plugin Dependency Graph",
  "ui.dep_graph.tt_back": "Back to project list",
  "ui.dep_graph.tt_tab_analytics": "Plugin usage analytics and insights",
  "ui.dep_graph.tt_tab_by_project": "Projects ranked by plugin count",
  "ui.dep_graph.tt_tab_most_used": "Plugins ranked by how many projects use them",
  "ui.dep_graph.tt_tab_orphaned": "Installed plugins not used in any scanned project",
  "ui.dep_graph.used_in_title": "Used in: {names}"
}
